dknovautils/__init__.py
dknovautils/__main__.py
dknovautils/commons.py
dknovautils/dk_cmdutils.py
dknovautils/dk_email2024.py
dknovautils/dk_homelan_utils.py
dknovautils/dk_imports.py
dknovautils/dk_lang_etc_util.py
dknovautils/dkat.py
dknovautils/dkfiles.py
dknovautils/dkipy.py
dknovautils/dknetwork.py
dknovautils/dkprocess.py
dknovautils/example.py
dknovautils/myadd.py
dknovautils/mysubtract.py
dknovautils/py.typed
dknovautils/z_test_files.py
dknovautils-0.2.68.dist-info/licenses/LICENSE
dknovautils-0.2.68.dist-info/METADATA
dknovautils-0.2.68.dist-info/WHEEL
dknovautils-0.2.68.dist-info/entry_points.txt
dknovautils-0.2.68.dist-info/top_level.txt
dknovautils-0.2.68.dist-info/RECORD
