Metadata-Version: 2.4
Name: dknovautils
Version: 0.2.68
Summary: A small example package
Author-email: dknova <dikisite@outlook.com>, dknova2 <dikisite2@outlook.com>
License: MIT License
Project-URL: Homepage, https://example.com/xxx
Project-URL: Documentation, https://readthedocs.org/xxx
Project-URL: Repository, https://github.com/me/xxx.git
Project-URL: Issues, https://github.com/me/xxx/issues
Project-URL: Changelog, https://github.com/me/xxx/blob/master/CHANGELOG.md
Classifier: Programming Language :: Python :: 3
Classifier: License :: OSI Approved :: MIT License
Classifier: Operating System :: OS Independent
Requires-Python: >=3.10
License-File: LICENSE
Requires-Dist: python-dateutil
Requires-Dist: numpy
Requires-Dist: urllib3
Requires-Dist: typing-extensions
Requires-Dist: dataclasses-json
Requires-Dist: atomics
Requires-Dist: scp
Requires-Dist: psutil
Requires-Dist: paramiko
Requires-Dist: pyperclip
Dynamic: license-file
